{
    "post": [
        {
            "question": "\"아침마다 마시고 있어요. 식단 도 같이 바꿔주니까 체지방만 5kg가 빠지네요!\" 이 후기는 바 리스타가 직접 OOO한 방탄커피 닥터바리스타의 후기입니다. 000에 들어갈 단어는 무엇일까 요?(힌트: ㅎㄷㄹ)",
            "answer": "정답은핸들링입니다."
        },
        {
            "question": "\"맛있어서 하루 3팩 이상 마실 뻔 했네요ㅎㅎ 한 달 동안 별 노 력 안했는데 한 달 동안 3kg 빠 졌어요!\" 이 후기는 OOO 방탄커 피들과 시중의 방탄커피들을 직 접 시음하고 레시피를 연구하여 만든 닥터바리스타의 후기입니 다. 000에 들어갈 단어는 무엇일까 요?",
            "answer": "정답은전세계입니다."
        },
        {
            "question": "",
            "answer": "정답은효능입니다."
        }
    ],
    "count": [
        3
    ]
}