{
    "post": [
        {
            "question": "2021년 겨울여행, 야놀자로 준 비해보세요! 6만원 상당의 숙박쿠폰팩 제공 은 기본! 0만원 이상만 구매하면! 디즈니 + 구독권을 뽑을 수 있는 100% 당첨뽑기 선물을 드려요. 0에 들어갈 숫자는 무엇일까요?",
            "answer": "정답은2입니다."
        },
        {
            "question": "2021년 연말 사랑하는 가족, 친구, 연인과 함께 함께 따뜻한 겨울 여행을 떠나보는건 어떨까요? 야놀자에서는 프리미엄 호텔/펜 션을 예약한 분들께 디즈니 +0 개월 구독권을 드리고 있어요. 연말느낌 물씬한 겨울여행도 즐 기고, 야놀자의 특별한 겨울선물 도 받아보세요! 0에 들어갈 숫자는 무엇일까요?",
            "answer": "정답은3입니다."
        },
        {
            "question": "올 겨울에는 경험하지 못한 역대 급 야놀자 혜택이 찾아갑니다! 연말호캉스와 겨울여행만 즐겨 도, 디즈니 + 구독권을 겨울선물 로 드려요! 2021년 연말, 가족 친구 연인과 함께 겨울여행 준비하고 야놀자 의 겨울선물도 받으세요! 숙소 예약하기 전에, 야놀자가 드리는 0만원 쿠폰팩도 잊지말 고 사용해주세요. 0에 들어갈 숫자는 무엇일까요?",
            "answer": "정답은6입니다."
        }
    ],
    "count": [
        3
    ]
}